{
    "info": {
        "_postman_id": "f159d47e-a256-401d-99f1-81979eb8feef",
        "name": "v! - Test 3",
        "schema": "https://schema.getpostman.com/json/collection/v2.1.0/collection.json"
    },
    "item": [
        {
            "name": "Sample endpoint: Returns details about a particular user",
            "id": "c8bb71ed-3627-4ba8-aa9e-6ae0600c015e",
            "request": {
                "method": "GET",
                "header": [],
                "url": {
                    "raw": "{{baseUrl}}/user?id=-85158857",
                    "host": [
                        "{{baseUrl}}"
                    ],
                    "path": [
                        "user"
                    ],
                    "query": [
                        {
                            "key": "id",
                            "value": "-85158857",
                            "description": "(Required) ID of the user"
                        }
                    ]
                }
            },
            "response": [
                {
                    "id": "9fdc2993-a04d-48cb-b355-542a45523301",
                    "name": "Sample response: Details about a user by ID",
                    "originalRequest": {
                        "method": "GET",
                        "header": [
                            {
                                "description": "Added as a part of security scheme: basic",
                                "key": "Authorization",
                                "value": "Basic <credentials>"
                            }
                        ],
                        "url": {
                            "raw": "{{baseUrl}}/user?id=-85158857",
                            "host": [
                                "{{baseUrl}}"
                            ],
                            "path": [
                                "user"
                            ],
                            "query": [
                                {
                                    "key": "id",
                                    "value": "-85158857"
                                }
                            ]
                        }
                    },
                    "status": "OK",
                    "code": 200,
                    "_postman_previewlanguage": "json",
                    "header": [
                        {
                            "disabled": false,
                            "description": "A link to the next page of responses",
                            "key": "x-next",
                            "value": "ipsum"
                        },
                        {
                            "key": "Content-Type",
                            "value": "application/json"
                        }
                    ],
                    "cookie": [],
                    "responseTime": null,
                    "body": "{\n \"id\": 54410744,\n \"name\": \"culpa sint in\",\n \"tag\": \"non Ut aliquip cupidatat voluptate\"\n}"
                },
                {
                    "id": "9b6b564f-2aaf-4770-ae0b-012764a6415a",
                    "name": "Unexpected error",
                    "originalRequest": {
                        "method": "GET",
                        "header": [
                            {
                                "description": "Added as a part of security scheme: basic",
                                "key": "Authorization",
                                "value": "Basic <credentials>"
                            }
                        ],
                        "url": {
                            "raw": "{{baseUrl}}/user?id=-85158857",
                            "host": [
                                "{{baseUrl}}"
                            ],
                            "path": [
                                "user"
                            ],
                            "query": [
                                {
                                    "key": "id",
                                    "value": "-85158857"
                                }
                            ]
                        }
                    },
                    "status": "Internal Server Error",
                    "code": 500,
                    "_postman_previewlanguage": "json",
                    "header": [
                        {
                            "key": "Content-Type",
                            "value": "application/json"
                        }
                    ],
                    "cookie": [],
                    "responseTime": null,
                    "body": "{\n \"code\": 90647256,\n \"message\": \"culpa labore\"\n}"
                }
            ]
        }
    ],
    "auth": {
        "type": "basic",
        "basic": [
            {
                "key": "username",
                "value": "<Basic Auth Username>",
                "type": "string"
            },
            {
                "key": "password",
                "value": "<Basic Auth Password>",
                "type": "string"
            }
        ]
    },
    "variable": [
        {
            "id": "c5490213-762c-40cd-a40e-b24ba09e0e66",
            "key": "baseUrl",
            "value": "https://petstore.swagger.io/v1",
            "type": "string"
        }
    ]
}